{
  "destination_en": "Maldives",
  "title_zh": "馬爾地夫 · 浪漫四天三夜之旅",
  "date_range": "2026/06/10–2026/06/13",
  "start_date": "2026-06-10",
  "end_date": "2026-06-13",
  "departure": "Taiwan (TPE)",
  "departure_code": "TPE",
  "destination_code": "MLE",
  "travelers": 2,
  "days": 4,
  "budget_ntd": 160000,
  "flight": {
    "airline": "新加坡航空 Singapore Airlines",
    "departure_date": "6月10日",
    "return_date": "6月13日",
    "total_price_ntd": 54000,
    "outbound": {
      "flight_no": "SQ 879",
      "route": "TPE → SIN 轉機 → MLE",
      "depart_time": "17:30",
      "arrive_time": "22:15 (+1)",
      "duration": "14h 45m (含轉機)",
      "class": "經濟艙"
    },
    "inbound": {
      "flight_no": "SQ 452",
      "route": "MLE → SIN 轉機 → TPE",
      "depart_time": "23:25",
      "arrive_time": "14:10 (+1)",
      "duration": "14h 45m (含轉機)",
      "class": "經濟艙"
    }
  },
  "hotels": [
    {
      "name": "Kurumba Maldives",
      "name_zh": "庫倫巴度假村",
      "district": "North Malé Atoll",
      "day_range": "1–3",
      "nights": 3,
      "price_ntd": 82000,
      "stars": "★★★★★",
      "room_type": "豪華海景別墅 Deluxe Ocean View Villa",
      "breakfast": "含自助早餐",
      "amenities": "🏖 私人沙灘 · 🏊 無邊際泳池 · 🧖 SPA · 🍽️ 多間餐廳 · 🚤 快艇接送",
      "search_query": "Kurumba Maldives resort",
      "photos": [
        {
          "url": "https://images.unsplash.com/photo-1590523277543-a94d2e4eb00b?crop=entropy&cs=tinysrgb&fit=max&fm=jpg&ixid=M3w5NDQ1NjR8MHwxfHNlYXJjaHwxfHxLdXJ1bWJhJTIwTWFsZGl2ZXMlMjByZXNvcnR8ZW58MHwwfHx8MTc3ODc3NDUxMnww&ixlib=rb-4.1.0&q=80&w=1080&w=400&h=300&fit=crop",
          "label": "brown wooden cottage on blue body of water during daytime"
        },
        {
          "url": "https://images.unsplash.com/photo-1467377791767-c929b5dc9a23?crop=entropy&cs=tinysrgb&fit=max&fm=jpg&ixid=M3w5NDQ1NjR8MHwxfHNlYXJjaHwyfHxLdXJ1bWJhJTIwTWFsZGl2ZXMlMjByZXNvcnR8ZW58MHwwfHx8MTc3ODc3NDUxMnww&ixlib=rb-4.1.0&q=80&w=1080&w=400&h=300&fit=crop",
          "label": "green palm trees near body of water"
        },
        {
          "url": "https://images.unsplash.com/photo-1602002418816-5c0aeef426aa?crop=entropy&cs=tinysrgb&fit=max&fm=jpg&ixid=M3w5NDQ1NjR8MHwxfHNlYXJjaHwzfHxLdXJ1bWJhJTIwTWFsZGl2ZXMlMjByZXNvcnR8ZW58MHwwfHx8MTc3ODc3NDUxMnww&ixlib=rb-4.1.0&q=80&w=1080&w=400&h=300&fit=crop",
          "label": "brown wooden bench on beach during daytime"
        },
        {
          "url": "https://images.unsplash.com/photo-1620065487644-1080510335f5?crop=entropy&cs=tinysrgb&fit=max&fm=jpg&ixid=M3w5NDQ1NjR8MHwxfHNlYXJjaHw0fHxLdXJ1bWJhJTIwTWFsZGl2ZXMlMjByZXNvcnR8ZW58MHwwfHx8MTc3ODc3NDUxMnww&ixlib=rb-4.1.0&q=80&w=1080&w=400&h=300&fit=crop",
          "label": "green palm trees near swimming pool during daytime"
        },
        {
          "url": "https://images.unsplash.com/photo-1643856555886-76dca68e5322?crop=entropy&cs=tinysrgb&fit=max&fm=jpg&ixid=M3w5NDQ1NjR8MHwxfHNlYXJjaHw1fHxLdXJ1bWJhJTIwTWFsZGl2ZXMlMjByZXNvcnR8ZW58MHwwfHx8MTc3ODc3NDUxMnww&ixlib=rb-4.1.0&q=80&w=1080&w=400&h=300&fit=crop",
          "label": "a white sandy beach surrounded by palm trees"
        },
        {
          "url": "https://images.unsplash.com/photo-1609601546193-f558f1ebb385?crop=entropy&cs=tinysrgb&fit=max&fm=jpg&ixid=M3w5NDQ1NjR8MHwxfHNlYXJjaHw2fHxLdXJ1bWJhJTIwTWFsZGl2ZXMlMjByZXNvcnR8ZW58MHwwfHx8MTc3ODc3NDUxMnww&ixlib=rb-4.1.0&q=80&w=1080&w=400&h=300&fit=crop",
          "label": "brown wooden dock on blue sea under white clouds during daytime"
        },
        {
          "url": "https://images.unsplash.com/photo-1590523277543-a94d2e4eb00b?crop=entropy&cs=tinysrgb&fit=max&fm=jpg&ixid=M3w5NDQ1NjR8MHwxfHNlYXJjaHwxfHxLdXJ1bWJhJTIwTWFsZGl2ZXMlMjByZXNvcnR8ZW58MHwwfHx8MTc3ODc3NDUxMnww&ixlib=rb-4.1.0&q=80&w=1080&w=400&h=300&fit=crop",
          "label": "brown wooden cottage on blue body of water during daytime"
        },
        {
          "url": "https://images.unsplash.com/photo-1467377791767-c929b5dc9a23?crop=entropy&cs=tinysrgb&fit=max&fm=jpg&ixid=M3w5NDQ1NjR8MHwxfHNlYXJjaHwyfHxLdXJ1bWJhJTIwTWFsZGl2ZXMlMjByZXNvcnR8ZW58MHwwfHx8MTc3ODc3NDUxMnww&ixlib=rb-4.1.0&q=80&w=1080&w=400&h=300&fit=crop",
          "label": "green palm trees near body of water"
        },
        {
          "url": "https://images.unsplash.com/photo-1602002418816-5c0aeef426aa?crop=entropy&cs=tinysrgb&fit=max&fm=jpg&ixid=M3w5NDQ1NjR8MHwxfHNlYXJjaHwzfHxLdXJ1bWJhJTIwTWFsZGl2ZXMlMjByZXNvcnR8ZW58MHwwfHx8MTc3ODc3NDUxMnww&ixlib=rb-4.1.0&q=80&w=1080&w=400&h=300&fit=crop",
          "label": "brown wooden bench on beach during daytime"
        },
        {
          "url": "https://images.unsplash.com/photo-1620065487644-1080510335f5?crop=entropy&cs=tinysrgb&fit=max&fm=jpg&ixid=M3w5NDQ1NjR8MHwxfHNlYXJjaHw0fHxLdXJ1bWJhJTIwTWFsZGl2ZXMlMjByZXNvcnR8ZW58MHwwfHx8MTc3ODc3NDUxMnww&ixlib=rb-4.1.0&q=80&w=1080&w=400&h=300&fit=crop",
          "label": "green palm trees near swimming pool during daytime"
        },
        {
          "url": "https://images.unsplash.com/photo-1643856555886-76dca68e5322?crop=entropy&cs=tinysrgb&fit=max&fm=jpg&ixid=M3w5NDQ1NjR8MHwxfHNlYXJjaHw1fHxLdXJ1bWJhJTIwTWFsZGl2ZXMlMjByZXNvcnR8ZW58MHwwfHx8MTc3ODc3NDUxMnww&ixlib=rb-4.1.0&q=80&w=1080&w=400&h=300&fit=crop",
          "label": "a white sandy beach surrounded by palm trees"
        },
        {
          "url": "https://images.unsplash.com/photo-1609601546193-f558f1ebb385?crop=entropy&cs=tinysrgb&fit=max&fm=jpg&ixid=M3w5NDQ1NjR8MHwxfHNlYXJjaHw2fHxLdXJ1bWJhJTIwTWFsZGl2ZXMlMjByZXNvcnR8ZW58MHwwfHx8MTc3ODc3NDUxMnww&ixlib=rb-4.1.0&q=80&w=1080&w=400&h=300&fit=crop",
          "label": "brown wooden dock on blue sea under white clouds during daytime"
        }
      ]
    }
  ],
  "restaurants": {
    "fine_dining": [
      {
        "name": "Ithaa Undersea Restaurant",
        "name_zh": "伊塔海底餐廳 · 康斯坦斯莫凡彼島",
        "stars": "⭐⭐⭐",
        "dish": "🦞 招牌：龍蝦三重奏 · 香檳配對",
        "address": "Conrad Maldives Rangali Island",
        "price_ntd": 14000,
        "price_label": "晚餐套餐 $280/人 · NT$14,000（兩人）",
        "hours": "12:00–14:30 / 18:00–22:00 · 需預約",
        "search_query": "Ithaa Undersea Restaurant Maldives",
        "photos": [
          {
            "url": "",
            "label": "fine dining food Maldives"
          },
          {
            "url": "",
            "label": "fine dining food Maldives"
          },
          {
            "url": "",
            "label": "fine dining food Maldives"
          }
        ]
      }
    ],
    "bistros": [
      {
        "name": "Vihamana Restaurant",
        "name_zh": "維哈馬納餐廳 · 庫倫巴度假村",
        "stars": "",
        "dish": "🐟 招牌：馬爾地夫烤魚 · 椰子咖喱",
        "address": "Kurumba Maldives",
        "price_ntd": 3600,
        "price_label": "自助晚餐 $72/人 · NT$3,600（兩人）",
        "hours": "18:30–21:30",
        "search_query": "Vihamana restaurant Kurumba",
        "photos": [
          {
            "url": "",
            "label": "bistros food Maldives"
          },
          {
            "url": "",
            "label": "bistros food Maldives"
          },
          {
            "url": "",
            "label": "bistros food Maldives"
          }
        ]
      }
    ],
    "cafes": [
      {
        "name": "Café Kurumba",
        "name_zh": "庫倫巴咖啡廳",
        "stars": "",
        "dish": "☕ 招牌：冰拿鐵 · 椰子鬆餅 · 熱帶水果拼盤",
        "address": "Kurumba Maldives",
        "price_ntd": 800,
        "price_label": "輕食飲品 $16/人 · NT$800（兩人）",
        "hours": "07:00–18:00",
        "search_query": "Cafe Kurumba Maldives",
        "photos": [
          {
            "url": "",
            "label": "cafe coffee Maldives"
          },
          {
            "url": "",
            "label": "cafe coffee Maldives"
          },
          {
            "url": "",
            "label": "cafe coffee Maldives"
          }
        ]
      }
    ]
  },
  "itinerary": [
    {
      "day": 1,
      "date": "June 10 · Wed",
      "label_zh": "抵達日 · 入住庫倫巴",
      "hotel_name": "Kurumba Maldives",
      "hotel_name_zh": "庫倫巴度假村 · 豪華海景別墅",
      "hotel_room": "豪華海景別墅 Deluxe Ocean View Villa",
      "weather": "☀️ 32°/27°",
      "rain_pct": "5%",
      "slots": [
        {
          "time": "17:30",
          "desc": "✈️ 桃園機場 TPE 出發 · 新加坡航空 SQ879"
        },
        {
          "time": "22:15",
          "desc": "🛬 抵達馬累國際機場 MLE · 入境通關"
        },
        {
          "time": "23:00",
          "desc": "🚤 快艇接駁至庫倫巴度假村（約15分鐘）"
        },
        {
          "time": "23:30",
          "desc": "🏨 辦理入住 · 迎賓飲料 · 海景別墅放鬆"
        },
        {
          "time": "00:00",
          "desc": "🌙 私人陽台觀星 · 聆聽海浪聲入眠"
        }
      ]
    },
    {
      "day": 2,
      "date": "June 11 · Thu",
      "label_zh": "全日海島奢華體驗",
      "hotel_name": "Kurumba Maldives",
      "hotel_name_zh": "庫倫巴度假村 · 豪華海景別墅",
      "hotel_room": "豪華海景別墅 Deluxe Ocean View Villa",
      "weather": "☀️ 33°/28°",
      "rain_pct": "0%",
      "slots": [
        {
          "time": "07:00",
          "desc": "🌅 日出瑜珈 · 沙灘冥想"
        },
        {
          "time": "08:00",
          "desc": "🥐 Café Kurumba 早餐 · 椰子鬆餅與冰拿鐵"
        },
        {
          "time": "09:30",
          "desc": "🏊 無邊際泳池暢游 · 沙灘躺椅日光浴"
        },
        {
          "time": "12:00",
          "desc": "🍽️ Vihamana Restaurant 自助午餐 · 馬爾地夫烤魚"
        },
        {
          "time": "14:00",
          "desc": "🐠 浮潛探索珊瑚礁 · 海龜與熱帶魚群"
        },
        {
          "time": "16:00",
          "desc": "💆 雙人SPA療程（60分鐘）"
        },
        {
          "time": "18:30",
          "desc": "🍹 日落雞尾酒 · 沙灘酒吧"
        },
        {
          "time": "20:00",
          "desc": "🦞 庫倫巴沙灘晚餐 · 燭光龍蝦套餐"
        }
      ]
    },
    {
      "day": 3,
      "date": "June 12 · Fri",
      "label_zh": "浪漫全日 · 海底晚餐",
      "hotel_name": "Kurumba Maldives",
      "hotel_name_zh": "庫倫巴度假村 · 豪華海景別墅",
      "hotel_room": "豪華海景別墅 Deluxe Ocean View Villa",
      "weather": "☀️ 32°/27°",
      "rain_pct": "10%",
      "slots": [
        {
          "time": "07:30",
          "desc": "🥐 別墅內早餐 · 漂浮早餐服務"
        },
        {
          "time": "09:00",
          "desc": "🚤 出海賞海豚 · 追逐寬吻海豚群"
        },
        {
          "time": "11:30",
          "desc": "🏖️ 無人沙洲野餐 · 香檳與水果"
        },
        {
          "time": "14:00",
          "desc": "🤿 深潛體驗（教練陪同）"
        },
        {
          "time": "16:00",
          "desc": "🏐 沙灘排球 · 或別墅內休息"
        },
        {
          "time": "18:00",
          "desc": "🚤 快艇前往康斯坦斯莫凡彼島"
        },
        {
          "time": "19:00",
          "desc": "🦞 Ithaa海底餐廳晚餐 · 龍蝦三重奏"
        },
        {
          "time": "21:30",
          "desc": "🚤 返回庫倫巴 · 星空漫步"
        }
      ]
    },
    {
      "day": 4,
      "date": "June 13 · Sat",
      "label_zh": "最後一日 · 返程",
      "hotel_name": "Kurumba Maldives",
      "hotel_name_zh": "庫倫巴度假村 · 豪華海景別墅",
      "hotel_room": "豪華海景別墅 Deluxe Ocean View Villa",
      "weather": "☀️ 32°/27°",
      "rain_pct": "5%",
      "slots": [
        {
          "time": "07:00",
          "desc": "🥐 最後早餐 · 沙灘漫步"
        },
        {
          "time": "09:00",
          "desc": "🏊 最後泳池時光 · 拍照留念"
        },
        {
          "time": "10:30",
          "desc": "🧳 退房 · 寄放行李"
        },
        {
          "time": "11:00",
          "desc": "🎁 紀念品店選購 · 椰子油／手工飾品"
        },
        {
          "time": "12:00",
          "desc": "🍽️ 午餐 · 輕食三明治"
        },
        {
          "time": "14:00",
          "desc": "🚤 快艇返回馬累機場"
        },
        {
          "time": "16:00",
          "desc": "✈️ 馬累機場 MLE 辦理登機"
        },
        {
          "time": "23:25",
          "desc": "✈️ 新加坡航空 SQ452 返台"
        }
      ]
    }
  ],
  "costs": [
    {
      "label": "✈️ 來回機票",
      "amount_ntd": 54000
    },
    {
      "label": "🏨 住宿（總計）",
      "amount_ntd": 82000
    },
    {
      "label": "🍽️ 餐飲",
      "amount_ntd": 12000
    },
    {
      "label": "🎫 景點門票",
      "amount_ntd": 6000
    },
    {
      "label": "🚤 交通",
      "amount_ntd": 4000
    },
    {
      "label": "🛍️ 購物伴手禮",
      "amount_ntd": 2000
    }
  ],
  "cost_total_ntd": 160000,
  "budget_remaining_ntd": 0,
  "photos": {
    "hero": [
      {
        "url": "https://images.unsplash.com/photo-1679656952793-023c511f46de?crop=entropy&cs=tinysrgb&fit=max&fm=jpg&ixid=M3w5NDQ1NjR8MHwxfHNlYXJjaHwxfHxNYWxkaXZlcyUyMHNreWxpbmUlMjBsYW5kbWFya3xlbnwwfDB8fHwxNzc4ODk0ODU4fDA&ixlib=rb-4.1.0&q=80&w=1080&w=400&h=300&fit=crop",
        "label": "a large body of water with a city in the background"
      },
      {
        "url": "https://images.unsplash.com/photo-1679656952793-023c511f46de?crop=entropy&cs=tinysrgb&fit=max&fm=jpg&ixid=M3w5NDQ1NjR8MHwxfHNlYXJjaHwxfHxNYWxkaXZlcyUyMHNreWxpbmUlMjBsYW5kbWFya3xlbnwwfDB8fHwxNzc4ODk0ODU4fDA&ixlib=rb-4.1.0&q=80&w=1080&w=400&h=300&fit=crop",
        "label": "a large body of water with a city in the background"
      }
    ],
    "destination": [
      {
        "url": "https://images.unsplash.com/photo-1590523277543-a94d2e4eb00b?crop=entropy&cs=tinysrgb&fit=max&fm=jpg&ixid=M3w5NDQ1NjR8MHwxfHNlYXJjaHwxfHxNYWxkaXZlcyUyMHRyYXZlbCUyMHNjZW5lcnl8ZW58MHwwfHx8MTc3ODg5NDg1OXww&ixlib=rb-4.1.0&q=80&w=1080&w=400&h=300&fit=crop",
        "label": "brown wooden cottage on blue body of water during daytime"
      },
      {
        "url": "https://images.unsplash.com/photo-1576158831003-d41033ec31fd?crop=entropy&cs=tinysrgb&fit=max&fm=jpg&ixid=M3w5NDQ1NjR8MHwxfHNlYXJjaHwyfHxNYWxkaXZlcyUyMHRyYXZlbCUyMHNjZW5lcnl8ZW58MHwwfHx8MTc3ODg5NDg1OXww&ixlib=rb-4.1.0&q=80&w=1080&w=400&h=300&fit=crop",
        "label": "person swinging on hammock hanged on coconut tree near sea"
      },
      {
        "url": "https://images.unsplash.com/photo-1467377791767-c929b5dc9a23?crop=entropy&cs=tinysrgb&fit=max&fm=jpg&ixid=M3w5NDQ1NjR8MHwxfHNlYXJjaHwzfHxNYWxkaXZlcyUyMHRyYXZlbCUyMHNjZW5lcnl8ZW58MHwwfHx8MTc3ODg5NDg1OXww&ixlib=rb-4.1.0&q=80&w=1080&w=400&h=300&fit=crop",
        "label": "green palm trees near body of water"
      },
      {
        "url": "https://images.unsplash.com/photo-1620065487644-1080510335f5?crop=entropy&cs=tinysrgb&fit=max&fm=jpg&ixid=M3w5NDQ1NjR8MHwxfHNlYXJjaHw0fHxNYWxkaXZlcyUyMHRyYXZlbCUyMHNjZW5lcnl8ZW58MHwwfHx8MTc3ODg5NDg1OXww&ixlib=rb-4.1.0&q=80&w=1080&w=400&h=300&fit=crop",
        "label": "green palm trees near swimming pool during daytime"
      },
      {
        "url": "https://images.unsplash.com/photo-1622779536320-bb5f5b501a06?crop=entropy&cs=tinysrgb&fit=max&fm=jpg&ixid=M3w5NDQ1NjR8MHwxfHNlYXJjaHw1fHxNYWxkaXZlcyUyMHRyYXZlbCUyMHNjZW5lcnl8ZW58MHwwfHx8MTc3ODg5NDg1OXww&ixlib=rb-4.1.0&q=80&w=1080&w=400&h=300&fit=crop",
        "label": "green trees near body of water under blue sky during daytime"
      },
      {
        "url": "https://images.unsplash.com/photo-1602002418816-5c0aeef426aa?crop=entropy&cs=tinysrgb&fit=max&fm=jpg&ixid=M3w5NDQ1NjR8MHwxfHNlYXJjaHw2fHxNYWxkaXZlcyUyMHRyYXZlbCUyMHNjZW5lcnl8ZW58MHwwfHx8MTc3ODg5NDg1OXww&ixlib=rb-4.1.0&q=80&w=1080&w=400&h=300&fit=crop",
        "label": "brown wooden bench on beach during daytime"
      },
      {
        "url": "https://images.unsplash.com/photo-1590523277543-a94d2e4eb00b?crop=entropy&cs=tinysrgb&fit=max&fm=jpg&ixid=M3w5NDQ1NjR8MHwxfHNlYXJjaHwxfHxNYWxkaXZlcyUyMHRyYXZlbCUyMHNjZW5lcnl8ZW58MHwwfHx8MTc3ODg5NDg1OXww&ixlib=rb-4.1.0&q=80&w=1080&w=400&h=300&fit=crop",
        "label": "brown wooden cottage on blue body of water during daytime"
      },
      {
        "url": "https://images.unsplash.com/photo-1576158831003-d41033ec31fd?crop=entropy&cs=tinysrgb&fit=max&fm=jpg&ixid=M3w5NDQ1NjR8MHwxfHNlYXJjaHwyfHxNYWxkaXZlcyUyMHRyYXZlbCUyMHNjZW5lcnl8ZW58MHwwfHx8MTc3ODg5NDg1OXww&ixlib=rb-4.1.0&q=80&w=1080&w=400&h=300&fit=crop",
        "label": "person swinging on hammock hanged on coconut tree near sea"
      },
      {
        "url": "https://images.unsplash.com/photo-1467377791767-c929b5dc9a23?crop=entropy&cs=tinysrgb&fit=max&fm=jpg&ixid=M3w5NDQ1NjR8MHwxfHNlYXJjaHwzfHxNYWxkaXZlcyUyMHRyYXZlbCUyMHNjZW5lcnl8ZW58MHwwfHx8MTc3ODg5NDg1OXww&ixlib=rb-4.1.0&q=80&w=1080&w=400&h=300&fit=crop",
        "label": "green palm trees near body of water"
      },
      {
        "url": "https://images.unsplash.com/photo-1620065487644-1080510335f5?crop=entropy&cs=tinysrgb&fit=max&fm=jpg&ixid=M3w5NDQ1NjR8MHwxfHNlYXJjaHw0fHxNYWxkaXZlcyUyMHRyYXZlbCUyMHNjZW5lcnl8ZW58MHwwfHx8MTc3ODg5NDg1OXww&ixlib=rb-4.1.0&q=80&w=1080&w=400&h=300&fit=crop",
        "label": "green palm trees near swimming pool during daytime"
      },
      {
        "url": "https://images.unsplash.com/photo-1622779536320-bb5f5b501a06?crop=entropy&cs=tinysrgb&fit=max&fm=jpg&ixid=M3w5NDQ1NjR8MHwxfHNlYXJjaHw1fHxNYWxkaXZlcyUyMHRyYXZlbCUyMHNjZW5lcnl8ZW58MHwwfHx8MTc3ODg5NDg1OXww&ixlib=rb-4.1.0&q=80&w=1080&w=400&h=300&fit=crop",
        "label": "green trees near body of water under blue sky during daytime"
      },
      {
        "url": "https://images.unsplash.com/photo-1602002418816-5c0aeef426aa?crop=entropy&cs=tinysrgb&fit=max&fm=jpg&ixid=M3w5NDQ1NjR8MHwxfHNlYXJjaHw2fHxNYWxkaXZlcyUyMHRyYXZlbCUyMHNjZW5lcnl8ZW58MHwwfHx8MTc3ODg5NDg1OXww&ixlib=rb-4.1.0&q=80&w=1080&w=400&h=300&fit=crop",
        "label": "brown wooden bench on beach during daytime"
      }
    ]
  },
  "chat_hash": "d6a4e79b56c212bb6e83b3632ed432fc67c2aff81a7fc3d2f1c77cf669cea254",
  "config_hash": "32a81935bd11e3366f0a7d66fded735f0412cb74915886bea371444885c19238",
  "generated_at": "2026-05-16T09:40:32.158770"
}